{
"Árvores altas e copas densas, filtrando a luz do sol em padrões cambiantes no chão de folhas secas.": 1,
"Clareira natural, onde a grama macia cresce entre raízes expostas e pequenas flores silvestres.": 1,
"Trilha estreita e bem batida, marcada por pegadas de animais e viajantes anteriores.": 1,
"Riacho de águas cristalinas, serpenteando entre pedras musgosas e troncos caídos.": 1,
"Área de mata aberta, onde arbustos espinhosos se misturam a samambaias e trepadeiras.": 1,
"Colina suave coberta por pinheiros, com o chão forrado por agulhas secas que abafam os passos.": 1,
"Lagoa pequena e parada, com libélulas pairando sobre a superfície e sapos escondidos entre os juncos.": 1,
"Troncos caídos em decomposição, cobertos por fungos coloridos e larvas brilhantes.": 1,
"Campo de samambaias gigantes, algumas tão altas quanto um homem, balançando ao vento.": 1,
"Área alagadiça, onde o chão encharcado emite um cheiro de terra úmida e vida microbiana.": 1,
"Bosque de bétulas brancas, suas cascas descascadas revelando marcas suaves e pálidas.": 1,
"Caminho pedregoso, com seixos lisos e arredondados pelo tempo, indicando um antigo leito de rio.": 1,
"Clareira com um grande carvalho solitário, sua sombra projetando um círculo perfeito de frescor.": 1,
"Vegetação rasteira espinhosa, dificultando a passagem sem ferir as pernas desprotegidas.": 1,
"Área onde a neblina matinal persiste, deixando o ar úmido e os sons abafados.": 1,
"Troncos marcados por garras de animais, indicando território ou locais de afiação.": 1,
"Pequena cascata, caindo sobre rochas escuras e formando uma piscina rasa e refrescante.": 1,
"Chão coberto por folhas úmidas, emitindo um cheiro adocicado de decomposição.": 1,
"Arbustos frutíferos, carregados com bagas vermelhas e roxas (algumas comestíveis, outras venenosas).": 1,
"Área de ventos fortes, onde os galhos mais altos rangem e as folhas sibilam como serpentes.": 1,
"Clareira com um ninho abandonado, grande o suficiente para pertencer a uma ave de rapina.": 1,
"Troncos escorregadios por musgo úmido, tornando escaladas ou passagens arriscadas.": 1,
"Região com muitas tocas pequenas, possivelmente de raposas, texugos ou roedores.": 1,
"Árvores jovens crescendo em círculo, como se algo antigo tivesse morrido ali antes.": 1,
"Lago raso com fundo lamacento, onde garças pescam e insetos saltam na superfície.": 1,
"Galhos baixos e entrelaçados, forçando os viajantes a se agacharem ou desviarem.": 1,
"Pedra grande e plana no meio da mata, quase como um altar natural ou ponto de descanso.": 1,
"Área onde o solo é arenoso e seco, contrastando com a umidade ao redor.": 1,
"Toca de animal grande, com marcas de arrasto e restos de ossos na entrada.": 1,
"Clareira com um antigo marco de pedra, coberto por líquens e inscrições desbotadas.": 1,
"Árvores retorcidas com cascas negras e raízes expostas, como garras agarrando o solo.": 1,
"Clareira de cogumelos brilhantes, emitindo uma luz azulada fraca.": 1,
"Troncos caídos cobertos por musgo, formando pontes naturais sobre riachos rasos.": 1,
"Área pantanosa com líquens flutuantes e bolhas de gás subindo à superfície.": 1,
"Colina coberta por flores negras, cujas pétalas se fecham ao toque.": 1,
"Pedras esculpidas pela erosão, formando rostos grotescos que parecem sussurrar.": 1,
"Campo de teias gigantes, onde insetos do tamanho de gatos ficam imobilizados.": 1,
"Árvores com frutos pulsantes, como corações expostos.": 1,
"Lagoa de água turva, onde sombras se movem sob a superfície.": 1,
"Clareira com um círculo de pedras, onde o vento assobia melodias estranhas.": 1,
"Trilha de pegadas enormes, como se algo colossal tivesse passado recentemente.": 1,
"Área onde o solo é coberto por ossos de pequenas criaturas.": 1,
"Árvores com galhos entrelaçados, formando arcos naturais como portais.": 1,
"Colmeias gigantes penduradas nos galhos, emitindo zumbidos perturbadores.": 1,
"Região onde a vegetação parece ter sido queimada por algo não natural.": 1,
"Pequeno santuário abandonado, com estátuas de deuses desconhecidos.": 1,
"Clareira onde o tempo parece parado, com gotas de água suspensas no ar.": 1,
"Floresta de bambus que rangem como ossos secos ao vento.": 1,
"Área onde as folhas são todas vermelhas, mesmo fora do outono.": 1,
"Tronco oco que ecoa como um tambor quando batido.": 1
}